mocap_settings/__init__.py
mocap_settings/axengine_1769785883_1408080803.py
mocap_settings/constants.py
mocap_settings/decoder_utils/calibration_utils.py
mocap_settings/decoder_utils/io_utils.py
mocap_settings/decoder_utils/mocap_utils.py
mocap_settings/decoder_utils/sync_utils.py
mocap_settings/impl/GeneralSettings.py
mocap_settings/impl/MDCCalibrationPipelineSettings.py
mocap_settings/impl/MDCPipelineSettings.py
mocap_settings/impl/NotifierSettings.py
mocap_settings/impl/OpsAnimationFilesExportsSettings.py
mocap_settings/impl/OpsBlendFilesCreationSettings.py
mocap_settings/impl/OpsBlenderFBXExportSettings.py
mocap_settings/impl/OpsCalibrateArucoSettings.py
mocap_settings/impl/OpsCalibrateCheckerboardSettings.py
mocap_settings/impl/OpsCalibrateSettings.py
mocap_settings/impl/OpsCorrectCalibSettings.py
mocap_settings/impl/OpsDetectMarkerObjectsSettings.py
mocap_settings/impl/OpsDetectObjectsSettings.py
mocap_settings/impl/OpsDownloadDatasetSettings.py
mocap_settings/impl/OpsDownloadInputsSettings.py
mocap_settings/impl/OpsExtractMoveFileSettings.py
mocap_settings/impl/OpsFinalizeARunSettings.py
mocap_settings/impl/OpsFloorPlaneRootAdjustmentSettings.py
mocap_settings/impl/OpsHand3dPoseOnTracksSettings.py
mocap_settings/impl/OpsHandsGen2Settings.py
mocap_settings/impl/OpsInputVideosAudiosSettings.py
mocap_settings/impl/OpsJerseyClassifySettings.py
mocap_settings/impl/OpsKalmanMonocularSettings.py
mocap_settings/impl/OpsKalmanSettings.py
mocap_settings/impl/OpsKalmanV2Settings.py
mocap_settings/impl/OpsMarkerKalmanFilterSettings.py
mocap_settings/impl/OpsMarkersToBlendSettings.py
mocap_settings/impl/OpsMayaExportSettings.py
mocap_settings/impl/OpsMdcDetectionsSettings.py
mocap_settings/impl/OpsMdcTrackingSettings.py
mocap_settings/impl/OpsMocapSettings.py
mocap_settings/impl/OpsOnFailureSettings.py
mocap_settings/impl/OpsOnlineBallTrackingSettings.py
mocap_settings/impl/OpsPose2dSingleFrameSettings.py
mocap_settings/impl/OpsPose3dMonoSettings.py
mocap_settings-1.26.0.dist-info/METADATA
mocap_settings-1.26.0.dist-info/WHEEL
mocap_settings-1.26.0.dist-info/RECORD
