Metadata-Version: 2.1
Name: mocap-settings
Version: 1.26.0
Summary: Motion capture service used for all moveai engine's operation settings.
Author: Move.ai
Author-email: info@move.ai
Requires-Python: >=3.10,<4.0
Classifier: Programming Language :: Python :: 3
Classifier: Programming Language :: Python :: 3.10
Classifier: Programming Language :: Python :: 3.11
Classifier: Programming Language :: Python :: 3.12
Requires-Dist: easydict (>=1.13,<2.0)
Requires-Dist: jsf (>=0.8.0,<0.9.0)
Requires-Dist: mocap-runtime (>=0.2.0,<0.3.0)
Requires-Dist: pydantic (>=2.4,<3.0)
Requires-Dist: pydantic-settings (>=2.1.0,<3.0.0)
Requires-Dist: pyyaml (>=6.0.1,<7.0.0)
